mcp_installer-0.5.0.dist-info/licenses/LICENSE
mcpi/__init__.py
mcpi/cli.py
mcpi/py.typed
mcpi/user_config.py
mcpi/bundles/__init__.py
mcpi/bundles/catalog.py
mcpi/bundles/installer.py
mcpi/bundles/models.py
mcpi/clients/__init__.py
mcpi/clients/base.py
mcpi/clients/claude_code.py
mcpi/clients/disabled_tracker.py
mcpi/clients/enable_disable_handlers.py
mcpi/clients/file_based.py
mcpi/clients/file_move_enable_disable_handler.py
mcpi/clients/manager.py
mcpi/clients/plugin_based.py
mcpi/clients/protocols.py
mcpi/clients/registry.py
mcpi/clients/types.py
mcpi/clients/schemas/claude-settings-schema.yaml
mcpi/clients/schemas/internal-config-schema.yaml
mcpi/clients/schemas/mcp-config-schema.yaml
mcpi/data/catalog.cue
mcpi/data/catalog.json
mcpi/data/bundles/ai-tools.json
mcpi/data/bundles/content.json
mcpi/data/bundles/data-science.json
mcpi/data/bundles/devops.json
mcpi/data/bundles/web-dev.json
mcpi/data/templates/brave-search/api-key.yaml
mcpi/data/templates/filesystem/custom-directories.yaml
mcpi/data/templates/filesystem/project-files.yaml
mcpi/data/templates/filesystem/user-documents.yaml
mcpi/data/templates/github/personal-full-access.yaml
mcpi/data/templates/github/public-repos.yaml
mcpi/data/templates/github/read-only.yaml
mcpi/data/templates/postgres/docker.yaml
mcpi/data/templates/postgres/local-development.yaml
mcpi/data/templates/postgres/production.yaml
mcpi/data/templates/slack/bot-token.yaml
mcpi/data/templates/slack/limited-channels.yaml
mcpi/installer/__init__.py
mcpi/installer/base.py
mcpi/installer/claude_code.py
mcpi/installer/git.py
mcpi/installer/npm.py
mcpi/installer/python.py
mcpi/registry/__init__.py
mcpi/registry/catalog.py
mcpi/registry/catalog_manager.py
mcpi/registry/cue_validator.py
mcpi/registry/validation.py
mcpi/templates/__init__.py
mcpi/templates/discovery.py
mcpi/templates/models.py
mcpi/templates/prompt_handler.py
mcpi/templates/recommender.py
mcpi/templates/template_manager.py
mcpi/tui/__init__.py
mcpi/tui/factory.py
mcpi/tui/protocol.py
mcpi/tui/adapters/__init__.py
mcp_installer-0.5.0.dist-info/METADATA
mcp_installer-0.5.0.dist-info/WHEEL
mcp_installer-0.5.0.dist-info/entry_points.txt
mcp_installer-0.5.0.dist-info/top_level.txt
mcp_installer-0.5.0.dist-info/RECORD
