Metadata-Version: 2.4
Name: mcp-installer
Version: 0.5.0
Summary: CLI Interface for MCP
Author-email: Brandon Fryslie <nunya@hotmail.com>
License-Expression: MIT
Keywords: mcp,model-context-protocol,claude-code,cli,server-management
Requires-Python: >=3.12
License-File: LICENSE
Requires-Dist: click>=8.1.0
Requires-Dist: pydantic>=2.0.0
Requires-Dist: httpx>=0.24.0
Requires-Dist: toml>=0.10.0
Requires-Dist: jsonschema>=4.0.0
Requires-Dist: rich>=13.0.0
Requires-Dist: platformdirs>=3.0.0
Requires-Dist: pyyaml>=6.0.0
Requires-Dist: beautifulsoup4>=4.12.0
Requires-Dist: markdownify>=0.11.0
Requires-Dist: typer>=0.20.0
Requires-Dist: referencing<0.37.0
Provides-Extra: dev
Requires-Dist: pytest>=7.0.0; extra == "dev"
Requires-Dist: pytest-asyncio>=0.21.0; extra == "dev"
Requires-Dist: pytest-cov>=4.0.0; extra == "dev"
Requires-Dist: black>=23.0.0; extra == "dev"
Requires-Dist: ruff>=0.1.0; extra == "dev"
Requires-Dist: mypy>=1.0.0; extra == "dev"
Requires-Dist: types-toml; extra == "dev"
Requires-Dist: types-pyyaml; extra == "dev"
Requires-Dist: pre-commit>=3.0.0; extra == "dev"
Dynamic: license-file
